{
 "id": null,
 "result": [
    {
    "url": "http://tx2.androidfilehost.com/dl/8MxsmgPonNpHIF5lf6qqkQ/1439157077/24052804347790610/ProjectX-v1.1.0-20150809-m8.zip",
    "timestamp": "1439115749",
    "api_level": "22",
    "md5sum": "8a2bac889ae30f06d4b5d0b93b39ab9d",
    "filename": "ProjectX-v1.1.0-20150809-m8.zip",
    "channel": "NIGHTLY",
    "changes": "https://raw.githubusercontent.com/ProjectX-Android/PXUpdater-API/lollipop-5.1/changelog.xml",
    "incremental": ""
    }
  ],
 "error": null
}
